README.rst
mailtest.py
setup.py
mailtest.egg-info/PKG-INFO
mailtest.egg-info/SOURCES.txt
mailtest.egg-info/dependency_links.txt
mailtest.egg-info/top_level.txt